{
  "id_sptag": "-587335586",
  "index_page": 0,
  "name_cl_sptag": "Camera",
  "name_parent": "Anime",
  "total_img": 19,
  "total_page": 0,
  "hc_lt_alb": "-760531221",
  "hc_lt_data_img": "2063739019",
  "hc_lt_nortag": "-1501280431",
  "hc_lt_sptag": "-1074566755",
  "lt_alb": [
    {
      "id_alb": "63410260",
      "name_alb": "Anime",
      "total_img": 85314
    }
  ],
  "lt_data_img": [
    {
      "hc_lt_id_alb": "-824026795",
      "hc_lt_id_nortag": "1471769326",
      "hc_lt_id_sptag": "772833885",
      "id_img": "Original_718212_crop2608_1792289949",
      "link_img": "UTb0sGqADnbLiHq9qhRMRkSRiLND0Tk7ctN8tpraiieJvPj2rRfgfyL/DP610uyta46gfzH+yBQ3KhCrigh885Vy4706IhQgSYlgwrgVRHU=",
      "thumb": "UTb0sGqADnbLiHq9qhRMRkSRiLND0Tk7ctN8tpraiieJvPj2rRfgfyL/DP610uytDvC6ViDxp24JUkWS9BIwypVy4706IhQgSYlgwrgVRHU=",
      "lt_id_alb": [
        "63410260"
      ],
      "list_id_nortag": [
        "-1638897763",
        "-1182628656"
      ],
      "lt_id_sptag": [
        "-587335586",
        "1755521698",
        "-353024394",
        "-1686571485",
        "1078827483"
      ]
    },
    {
      "hc_lt_id_alb": "-824026795",
      "hc_lt_id_nortag": "-1131068287",
      "hc_lt_id_sptag": "-1825593971",
      "id_img": "Original_935313_crop2608_896177978",
      "link_img": "UTb0sGqADnbLiHq9qhRMRkSRiLND0Tk7ctN8tpraiifOjQhs+DUHo66gAiFzBReSLT2TcgZK3YtQb+QcsrXra5Vy4706IhQgSYlgwrgVRHU=",
      "thumb": "UTb0sGqADnbLiHq9qhRMRkSRiLND0Tk7ctN8tpraiifOjQhs+DUHo66gAiFzBReSLGxNPOVcRvE7jvTckB0i1JVy4706IhQgSYlgwrgVRHU=",
      "lt_id_alb": [
        "63410260"
      ],
      "list_id_nortag": [
        "-1182628656"
      ],
      "lt_id_sptag": [
        "-587335586",
        "-1230434216",
        "29436897",
        "-353024394",
        "376240968",
        "-1686571485",
        "1541647243",
        "1813151526",
        "1078827483",
        "491824726"
      ]
    },
    {
      "hc_lt_id_alb": "-824026795",
      "hc_lt_id_nortag": "-143917950",
      "hc_lt_id_sptag": "-765481117",
      "id_img": "Original_533720_crop2608_-1018494030",
      "link_img": "UTb0sGqADnbLiHq9qhRMRkSRiLND0Tk7ctN8tpraiieHoxK9HtLL4pcuEenWG/NUTTlznqBoFcC65aVd1/pNepVy4706IhQgSYlgwrgVRHU=",
      "thumb": "UTb0sGqADnbLiHq9qhRMRkSRiLND0Tk7ctN8tpraiieHoxK9HtLL4pcuEenWG/NU04Rn4eNV9Ib2rndbwAfmNZVy4706IhQgSYlgwrgVRHU=",
      "lt_id_alb": [
        "63410260"
      ],
      "list_id_nortag": [
        "-467032699",
        "766871050"
      ],
      "lt_id_sptag": [
        "-587335586",
        "912955984",
        "255859507",
        "1447453426",
        "587437740"
      ]
    },
    {
      "hc_lt_id_alb": "-824026795",
      "hc_lt_id_nortag": "-1837172718",
      "hc_lt_id_sptag": "-283751519",
      "id_img": "Charlotte_728037_crop2608_959208156",
      "link_img": "UTb0sGqADnbLiHq9qhRMRkSRiLND0Tk7ctN8tpraiida9Ko5lSOpWr1XMOO7i/ICByOZD1mhS4ZmDbZtM5SLs5Vy4706IhQgSYlgwrgVRHU=",
      "thumb": "UTb0sGqADnbLiHq9qhRMRkSRiLND0Tk7ctN8tpraiida9Ko5lSOpWr1XMOO7i/ICxSAz7VsUEg7S5AxOS+AUzZVy4706IhQgSYlgwrgVRHU=",
      "lt_id_alb": [
        "63410260"
      ],
      "list_id_nortag": [
        "-1903436891",
        "-1182628656"
      ],
      "lt_id_sptag": [
        "1271392973",
        "-587335586",
        "-353024394",
        "-1823594757",
        "-899599709",
        "1078827483",
        "491824726",
        "2085225201",
        "1114479900",
        "545210329"
      ]
    },
    {
      "hc_lt_id_alb": "-824026795",
      "hc_lt_id_nortag": "1521156541",
      "hc_lt_id_sptag": "1791313108",
      "id_img": "Original_847060_crop2608_1240437341",
      "link_img": "UTb0sGqADnbLiHq9qhRMRkSRiLND0Tk7ctN8tpraiifUCR7qlewPCqjpkcVsEH+HIbB7BMrDItNG0lix+hfkEJVy4706IhQgSYlgwrgVRHU=",
      "thumb": "UTb0sGqADnbLiHq9qhRMRkSRiLND0Tk7ctN8tpraiifUCR7qlewPCqjpkcVsEH+HEUUyfQiVCJQKPj60dgY0J5Vy4706IhQgSYlgwrgVRHU=",
      "lt_id_alb": [
        "63410260"
      ],
      "list_id_nortag": [
        "1911116961",
        "-1182628656"
      ],
      "lt_id_sptag": [
        "-587335586",
        "-1230434216",
        "-729883027",
        "-1546073662",
        "-510858498",
        "-353024394",
        "-67611207",
        "929761085",
        "1813151526",
        "768898453",
        "491824726"
      ]
    },
    {
      "hc_lt_id_alb": "-824026795",
      "hc_lt_id_nortag": "132699670",
      "hc_lt_id_sptag": "193829189",
      "id_img": "Original_857074_crop2608_1241360897",
      "link_img": "UTb0sGqADnbLiHq9qhRMRkSRiLND0Tk7ctN8tpraiielAmXKk/aBcfgqSwiGUjzjHRBZZVzCTyxjsiVsRnWQ0pVy4706IhQgSYlgwrgVRHU=",
      "thumb": "UTb0sGqADnbLiHq9qhRMRkSRiLND0Tk7ctN8tpraiielAmXKk/aBcfgqSwiGUjzjqme8o/+biOVOtr/V7MO1iJVy4706IhQgSYlgwrgVRHU=",
      "lt_id_alb": [
        "63410260"
      ],
      "list_id_nortag": [
        "-1496346654",
        "-1182628656"
      ],
      "lt_id_sptag": [
        "-587335586",
        "117222074",
        "-353024394",
        "376240968",
        "-1353196196",
        "-260062140",
        "-1165766878",
        "1078827483",
        "-1456680780",
        "491824726",
        "2108229313",
        "-2046828957",
        "2137211747"
      ]
    },
    {
      "hc_lt_id_alb": "-824026795",
      "hc_lt_id_nortag": "-324199368",
      "hc_lt_id_sptag": "-1403616835",
      "id_img": "Vocaloid_696799_crop2608_287269472",
      "link_img": "UTb0sGqADnbLiHq9qhRMRkSRiLND0Tk7ctN8tpraiid3xX3dmHhx7IKmMZb//MGkj4XZDNBKRJjewcvuljqnSZVy4706IhQgSYlgwrgVRHU=",
      "thumb": "UTb0sGqADnbLiHq9qhRMRkSRiLND0Tk7ctN8tpraiid3xX3dmHhx7IKmMZb//MGkL5xtN7Sh0G80gAMSTDQ1HJVy4706IhQgSYlgwrgVRHU=",
      "lt_id_alb": [
        "63410260"
      ],
      "list_id_nortag": [
        "-324062098",
        "-1182628656"
      ],
      "lt_id_sptag": [
        "177416588",
        "-1216236529",
        "-587335586",
        "1443880616",
        "29436897",
        "-1910110731",
        "-353024394",
        "376240968",
        "-67611207",
        "-1450260536",
        "-1501705937",
        "929761085",
        "1541647243",
        "680065126",
        "1508952095",
        "1447453426",
        "1677155011",
        "-1046579185",
        "1078827483",
        "-1456680780",
        "1257535371"
      ]
    },
    {
      "hc_lt_id_alb": "-824026795",
      "hc_lt_id_nortag": "-2092928010",
      "hc_lt_id_sptag": "911336458",
      "id_img": "Original_907716_crop2608_-1513558788",
      "link_img": "UTb0sGqADnbLiHq9qhRMRkSRiLND0Tk7ctN8tpraiie2MWXSAqv3ORczuF6efHYlMk4Tji7ZwyVRS5AmocojYpVy4706IhQgSYlgwrgVRHU=",
      "thumb": "UTb0sGqADnbLiHq9qhRMRkSRiLND0Tk7ctN8tpraiie2MWXSAqv3ORczuF6efHYl31+XADy0E8BV7HiYERtHH5Vy4706IhQgSYlgwrgVRHU=",
      "lt_id_alb": [
        "63410260"
      ],
      "list_id_nortag": [
        "-1182628656",
        "-1556851449"
      ],
      "lt_id_sptag": [
        "-1915687819",
        "1545739930",
        "-587335586",
        "-353024394",
        "1367612750",
        "-67611207",
        "1813151526",
        "1447453426",
        "1078827483",
        "-1456680780",
        "491824726",
        "-1602093195"
      ]
    },
    {
      "hc_lt_id_alb": "-824026795",
      "hc_lt_id_nortag": "-1131068287",
      "hc_lt_id_sptag": "-1566251329",
      "id_img": "Girl_935124_crop2608_1554059995",
      "link_img": "UTb0sGqADnbLiHq9qhRMRkSRiLND0Tk7ctN8tpraiiejw6VSZyeCaL4O8Ots4reWe/hsa25uyhTzUwwE9oheS5Vy4706IhQgSYlgwrgVRHU=",
      "thumb": "UTb0sGqADnbLiHq9qhRMRkSRiLND0Tk7ctN8tpraiiejw6VSZyeCaL4O8Ots4reWHTevB33oaXuJoTtQhAwYbZVy4706IhQgSYlgwrgVRHU=",
      "lt_id_alb": [
        "63410260"
      ],
      "list_id_nortag": [
        "-1182628656"
      ],
      "lt_id_sptag": [
        "177416588",
        "-1216236529",
        "-587335586",
        "-353024394",
        "376240968",
        "680065126",
        "-1353196196",
        "-260062140",
        "1078827483",
        "491824726",
        "2137211747"
      ]
    },
    {
      "hc_lt_id_alb": "-824026795",
      "hc_lt_id_nortag": "567546272",
      "hc_lt_id_sptag": "477198825",
      "id_img": "Charlotte_687123_crop2608_1721844738",
      "link_img": "UTb0sGqADnbLiHq9qhRMRkSRiLND0Tk7ctN8tpraiie39BmSgXGYvRRYagaFbCUEf960zpjsXfYbVAH6b+QXd5Vy4706IhQgSYlgwrgVRHU=",
      "thumb": "UTb0sGqADnbLiHq9qhRMRkSRiLND0Tk7ctN8tpraiie39BmSgXGYvRRYagaFbCUEzm23YVotd96EbV18tT4rd5Vy4706IhQgSYlgwrgVRHU=",
      "lt_id_alb": [
        "63410260"
      ],
      "list_id_nortag": [
        "1728965817",
        "-1903436891"
      ],
      "lt_id_sptag": [
        "1596260003",
        "177416588",
        "959633935",
        "-587335586",
        "29436897",
        "1136471916",
        "1913692055",
        "-2046828957",
        "2137211747",
        "26918368",
        "2085225201",
        "545210329"
      ]
    },
    {
      "hc_lt_id_alb": "-824026795",
      "hc_lt_id_nortag": "1362695760",
      "hc_lt_id_sptag": "477198825",
      "id_img": "Charlotte_687123_crop2608_2065390608",
      "link_img": "UTb0sGqADnbLiHq9qhRMRkSRiLND0Tk7ctN8tpraiiePsPW4RyfIJDfnvY7EwJTd+fYHH/jlqV6BeCKHBiB7vpVy4706IhQgSYlgwrgVRHU=",
      "thumb": "UTb0sGqADnbLiHq9qhRMRkSRiLND0Tk7ctN8tpraiiePsPW4RyfIJDfnvY7EwJTd1s8GvwMPJk4TgDKuZvc31JVy4706IhQgSYlgwrgVRHU=",
      "lt_id_alb": [
        "63410260"
      ],
      "list_id_nortag": [
        "-1903436891"
      ],
      "lt_id_sptag": [
        "1596260003",
        "177416588",
        "959633935",
        "-587335586",
        "29436897",
        "1136471916",
        "1913692055",
        "-2046828957",
        "2137211747",
        "26918368",
        "2085225201",
        "545210329"
      ]
    },
    {
      "hc_lt_id_alb": "-824026795",
      "hc_lt_id_nortag": "-2092928010",
      "hc_lt_id_sptag": "-1844210004",
      "id_img": "Original_908088_crop2608_342467247",
      "link_img": "UTb0sGqADnbLiHq9qhRMRkSRiLND0Tk7ctN8tpraiieGEgHf8kH3U8DS9fcY/SHvmswIFkM+02Tve5ElnzC93JVy4706IhQgSYlgwrgVRHU=",
      "thumb": "UTb0sGqADnbLiHq9qhRMRkSRiLND0Tk7ctN8tpraiieGEgHf8kH3U8DS9fcY/SHv64fAiYYNSimM5liQA7yYgJVy4706IhQgSYlgwrgVRHU=",
      "lt_id_alb": [
        "63410260"
      ],
      "list_id_nortag": [
        "-1182628656",
        "-1556851449"
      ],
      "lt_id_sptag": [
        "-587335586",
        "-510858498",
        "-353024394",
        "-1686571485",
        "63311442",
        "1961606085",
        "1541647243",
        "-260062140",
        "768898453",
        "467732324"
      ]
    },
    {
      "hc_lt_id_alb": "-824026795",
      "hc_lt_id_nortag": "-1131068287",
      "hc_lt_id_sptag": "517917689",
      "id_img": "Original_960166_crop2608_-1683478018",
      "link_img": "UTb0sGqADnbLiHq9qhRMRkSRiLND0Tk7ctN8tpraiieZVK68kQVIPa/43rnnYICOtY8eUcHr4Wn9PE8IFkcfmZVy4706IhQgSYlgwrgVRHU=",
      "thumb": "UTb0sGqADnbLiHq9qhRMRkSRiLND0Tk7ctN8tpraiieZVK68kQVIPa/43rnnYICOthdlJ0toNKJS7uGkHn24v5Vy4706IhQgSYlgwrgVRHU=",
      "lt_id_alb": [
        "63410260"
      ],
      "list_id_nortag": [
        "-1182628656"
      ],
      "lt_id_sptag": [
        "-587335586",
        "1755521698",
        "-442593670",
        "-353024394",
        "-1450260536"
      ]
    },
    {
      "hc_lt_id_alb": "-824026795",
      "hc_lt_id_nortag": "1471769326",
      "hc_lt_id_sptag": "-285414261",
      "id_img": "Original_718212_crop2608_1845658901",
      "link_img": "UTb0sGqADnbLiHq9qhRMRkSRiLND0Tk7ctN8tpraiice8C1jIKsOzvt5JITQ085w/Sd9n5GgRWto1V6yCB0zS5Vy4706IhQgSYlgwrgVRHU=",
      "thumb": "UTb0sGqADnbLiHq9qhRMRkSRiLND0Tk7ctN8tpraiice8C1jIKsOzvt5JITQ085wDtkaz/LBwboGp1sgNDXbTJVy4706IhQgSYlgwrgVRHU=",
      "lt_id_alb": [
        "63410260"
      ],
      "list_id_nortag": [
        "-1638897763",
        "-1182628656"
      ],
      "lt_id_sptag": [
        "-587335586",
        "1755521698",
        "-353024394",
        "376240968",
        "-1686571485",
        "-1450260536",
        "1078827483"
      ]
    },
    {
      "hc_lt_id_alb": "-824026795",
      "hc_lt_id_nortag": "1428677737",
      "hc_lt_id_sptag": "-1461051842",
      "id_img": "Original_905253_crop2608_34147186",
      "link_img": "UTb0sGqADnbLiHq9qhRMRkSRiLND0Tk7ctN8tpraiidW7YfGayxlY/LOr/9MQuJdldlJUaPBSAnEk61H/3UXypVy4706IhQgSYlgwrgVRHU=",
      "thumb": "UTb0sGqADnbLiHq9qhRMRkSRiLND0Tk7ctN8tpraiidW7YfGayxlY/LOr/9MQuJdJO8j/AJ2VaCMmo9O+DOnB5Vy4706IhQgSYlgwrgVRHU=",
      "lt_id_alb": [
        "63410260"
      ],
      "list_id_nortag": [
        "-467032699",
        "-1556851449"
      ],
      "lt_id_sptag": [
        "-333189356",
        "-587335586"
      ]
    },
    {
      "hc_lt_id_alb": "-824026795",
      "hc_lt_id_nortag": "-1837172718",
      "hc_lt_id_sptag": "-2125941288",
      "id_img": "Charlotte_780090_crop2608_-1157177379",
      "link_img": "UTb0sGqADnbLiHq9qhRMRkSRiLND0Tk7ctN8tpraiie83nStjG5ZbgHnvnd+uu/yLrugsSmhp+Hnj3AIspQ3t5Vy4706IhQgSYlgwrgVRHU=",
      "thumb": "UTb0sGqADnbLiHq9qhRMRkSRiLND0Tk7ctN8tpraiie83nStjG5ZbgHnvnd+uu/ypFxcR/OhobS8tjXK6n6PwZVy4706IhQgSYlgwrgVRHU=",
      "lt_id_alb": [
        "63410260"
      ],
      "list_id_nortag": [
        "-1903436891",
        "-1182628656"
      ],
      "lt_id_sptag": [
        "1271392973",
        "177416588",
        "-587335586",
        "29436897",
        "-353024394",
        "376240968",
        "1913692055",
        "-67611207",
        "1541647243",
        "-1353196196",
        "-1165766878",
        "-1823594757",
        "1078827483",
        "-1456680780",
        "491824726",
        "2137211747",
        "2085225201",
        "545210329"
      ]
    },
    {
      "hc_lt_id_alb": "-824026795",
      "hc_lt_id_nortag": "1531712947",
      "hc_lt_id_sptag": "919955477",
      "id_img": "Original_687714_crop2608_-669907891",
      "link_img": "UTb0sGqADnbLiHq9qhRMRkSRiLND0Tk7ctN8tpraiidhP5bHR7O0hYP1X4PNftvl6mCUUv/j1oy3eQ6z2gQpnJVy4706IhQgSYlgwrgVRHU=",
      "thumb": "UTb0sGqADnbLiHq9qhRMRkSRiLND0Tk7ctN8tpraiidhP5bHR7O0hYP1X4PNftvlbm1qqpSwARrt57CiyDWMzZVy4706IhQgSYlgwrgVRHU=",
      "lt_id_alb": [
        "63410260"
      ],
      "list_id_nortag": [
        "766871050",
        "-1182628656"
      ],
      "lt_id_sptag": [
        "-587335586",
        "-1230434216",
        "-353024394",
        "-2114154352",
        "1813151526",
        "-1331370225",
        "-899599709",
        "1078827483"
      ]
    },
    {
      "hc_lt_id_alb": "-824026795",
      "hc_lt_id_nortag": "1398358615",
      "hc_lt_id_sptag": "-171562943",
      "id_img": "DarlingintheFranXX_902858_crop2608_1890849975",
      "link_img": "UTb0sGqADnbLiHq9qhRMRkSRiLND0Tk7ctN8tpraiicZnxNflxB37G5if58TT9Q5sOffEY+8h1enPkRoTFkb95Vy4706IhQgSYlgwrgVRHU=",
      "thumb": "UTb0sGqADnbLiHq9qhRMRkSRiLND0Tk7ctN8tpraiicZnxNflxB37G5if58TT9Q5pt8UeStfo30ouCDYvrXhhJVy4706IhQgSYlgwrgVRHU=",
      "lt_id_alb": [
        "63410260"
      ],
      "list_id_nortag": [
        "-1182628656",
        "416018215"
      ],
      "lt_id_sptag": [
        "177416588",
        "-587335586",
        "606716576",
        "-1230434216",
        "-510858498",
        "748300120",
        "-353024394",
        "376240968",
        "-1985234469",
        "-2114154352",
        "768898453",
        "1078827483",
        "-1358769180"
      ]
    },
    {
      "hc_lt_id_alb": "-824026795",
      "hc_lt_id_nortag": "1531712947",
      "hc_lt_id_sptag": "-1638064713",
      "id_img": "Original_687714_crop2608_-1468030107",
      "link_img": "UTb0sGqADnbLiHq9qhRMRkSRiLND0Tk7ctN8tpraiidmDWf1/f8TgvXrGKX44DwLSS2vIw5pKyvIC7HGRjX0M5Vy4706IhQgSYlgwrgVRHU=",
      "thumb": "UTb0sGqADnbLiHq9qhRMRkSRiLND0Tk7ctN8tpraiidmDWf1/f8TgvXrGKX44DwL0WlIIg3G43OLe3kl1bQfxJVy4706IhQgSYlgwrgVRHU=",
      "lt_id_alb": [
        "63410260"
      ],
      "list_id_nortag": [
        "766871050",
        "-1182628656"
      ],
      "lt_id_sptag": [
        "-587335586",
        "-442593670",
        "-353024394",
        "-1686571485",
        "1568092380",
        "-2114154352",
        "-1331370225",
        "1078827483",
        "491824726"
      ]
    }
  ],
  "lt_nortag": [
    {
      "id_nortag": "-467032699",
      "name_cl_nortag": "Boy",
      "total_img": 8592,
      "name_parent": "Anime"
    },
    {
      "id_nortag": "-1903436891",
      "name_cl_nortag": "Charlotte",
      "total_img": 58,
      "name_parent": "Anime"
    },
    {
      "id_nortag": "1728965817",
      "name_cl_nortag": "Couple",
      "total_img": 2059,
      "name_parent": "Anime"
    },
    {
      "id_nortag": "416018215",
      "name_cl_nortag": "Darling in the FranXX",
      "total_img": 241,
      "name_parent": "Anime"
    },
    {
      "id_nortag": "-1182628656",
      "name_cl_nortag": "Girls",
      "total_img": 68557,
      "name_parent": "Anime"
    },
    {
      "id_nortag": "-1556851449",
      "name_cl_nortag": "Original 10",
      "total_img": 637,
      "name_parent": "Anime"
    },
    {
      "id_nortag": "-1638897763",
      "name_cl_nortag": "Original 3",
      "total_img": 1138,
      "name_parent": "Anime"
    },
    {
      "id_nortag": "1911116961",
      "name_cl_nortag": "Original 7",
      "total_img": 594,
      "name_parent": "Anime"
    },
    {
      "id_nortag": "-1496346654",
      "name_cl_nortag": "Original 8",
      "total_img": 450,
      "name_parent": "Anime"
    },
    {
      "id_nortag": "766871050",
      "name_cl_nortag": "Original",
      "total_img": 1020,
      "name_parent": "Anime"
    },
    {
      "id_nortag": "-324062098",
      "name_cl_nortag": "Vocaloid",
      "total_img": 1338,
      "name_parent": "Anime"
    }
  ],
  "lt_sptag": [
    {
      "id_sptag": "-1910110731",
      "name_cl_sptag": "Animal",
      "name_parent": "Anime",
      "total": 42
    },
    {
      "id_sptag": "2108229313",
      "name_cl_sptag": "Bag",
      "name_parent": "Anime",
      "total": 124
    },
    {
      "id_sptag": "1447453426",
      "name_cl_sptag": "Bird",
      "name_parent": "Anime",
      "total": 95
    },
    {
      "id_sptag": "2137211747",
      "name_cl_sptag": "Blonde",
      "name_parent": "Anime",
      "total": 908
    },
    {
      "id_sptag": "255859507",
      "name_cl_sptag": "Blood",
      "name_parent": "Anime",
      "total": 37
    },
    {
      "id_sptag": "-67611207",
      "name_cl_sptag": "Blush",
      "name_parent": "Anime",
      "total": 893
    },
    {
      "id_sptag": "1913692055",
      "name_cl_sptag": "bow Clothing",
      "name_parent": "Anime",
      "total": 452
    },
    {
      "id_sptag": "-587335586",
      "name_cl_sptag": "Camera",
      "name_parent": "Anime",
      "total": 19
    },
    {
      "id_sptag": "-1046579185",
      "name_cl_sptag": "Cat",
      "name_parent": "Anime",
      "total": 128
    },
    {
      "id_sptag": "545210329",
      "name_cl_sptag": "Charlotte Anime",
      "name_parent": "Anime",
      "total": 28
    },
    {
      "id_sptag": "-1602093195",
      "name_cl_sptag": "Cherry Blossom",
      "name_parent": "Anime",
      "total": 92
    },
    {
      "id_sptag": "748300120",
      "name_cl_sptag": "Coat",
      "name_parent": "Anime",
      "total": 64
    },
    {
      "id_sptag": "1961606085",
      "name_cl_sptag": "Coffee",
      "name_parent": "Anime",
      "total": 14
    },
    {
      "id_sptag": "912955984",
      "name_cl_sptag": "Crow",
      "name_parent": "Anime",
      "total": 5
    },
    {
      "id_sptag": "1114479900",
      "name_cl_sptag": "Cute",
      "name_parent": "Anime",
      "total": 61
    },
    {
      "id_sptag": "-333189356",
      "name_cl_sptag": "Flower",
      "name_parent": "Anime",
      "total": 497
    },
    {
      "id_sptag": "587437740",
      "name_cl_sptag": "Gas Mask",
      "name_parent": "Anime",
      "total": 6
    },
    {
      "id_sptag": "491824726",
      "name_cl_sptag": "Girls Cute Cool",
      "name_parent": "Anime",
      "total": 31431
    },
    {
      "id_sptag": "-899599709",
      "name_cl_sptag": "Girls Eyes Black",
      "name_parent": "Anime",
      "total": 5810
    },
    {
      "id_sptag": "376240968",
      "name_cl_sptag": "Girls Eyes Blue",
      "name_parent": "Anime",
      "total": 25656
    },
    {
      "id_sptag": "1545739930",
      "name_cl_sptag": "Girls Eyes Brown",
      "name_parent": "Anime",
      "total": 9376
    },
    {
      "id_sptag": "1568092380",
      "name_cl_sptag": "Girls Eyes Orange",
      "name_parent": "Anime",
      "total": 3828
    },
    {
      "id_sptag": "467732324",
      "name_cl_sptag": "Girls Eyes Pink",
      "name_parent": "Anime",
      "total": 1874
    },
    {
      "id_sptag": "-1915687819",
      "name_cl_sptag": "Girls Eyes Red",
      "name_parent": "Anime",
      "total": 12697
    },
    {
      "id_sptag": "-729883027",
      "name_cl_sptag": "Girls Eyes Violet",
      "name_parent": "Anime",
      "total": 6410
    },
    {
      "id_sptag": "1755521698",
      "name_cl_sptag": "Girls Eyes Yellow",
      "name_parent": "Anime",
      "total": 6605
    },
    {
      "id_sptag": "-1686571485",
      "name_cl_sptag": "Girls Hair Black",
      "name_parent": "Anime",
      "total": 16737
    },
    {
      "id_sptag": "-1450260536",
      "name_cl_sptag": "Girls Hair Blue",
      "name_parent": "Anime",
      "total": 9528
    },
    {
      "id_sptag": "1813151526",
      "name_cl_sptag": "Girls Hair Brow",
      "name_parent": "Anime",
      "total": 13760
    },
    {
      "id_sptag": "-1353196196",
      "name_cl_sptag": "Girls Hair Orange",
      "name_parent": "Anime",
      "total": 4128
    },
    {
      "id_sptag": "-1358769180",
      "name_cl_sptag": "Girls Hair Pink",
      "name_parent": "Anime",
      "total": 5690
    },
    {
      "id_sptag": "-1823594757",
      "name_cl_sptag": "Girls Hair Silver",
      "name_parent": "Anime",
      "total": 16300
    },
    {
      "id_sptag": "1271392973",
      "name_cl_sptag": "Girls Hair White",
      "name_parent": "Anime",
      "total": 8666
    },
    {
      "id_sptag": "-1165766878",
      "name_cl_sptag": "Girls Hair Yellow",
      "name_parent": "Anime",
      "total": 12651
    },
    {
      "id_sptag": "117222074",
      "name_cl_sptag": "Girls Hats",
      "name_parent": "Anime",
      "total": 11965
    },
    {
      "id_sptag": "-442593670",
      "name_cl_sptag": "Girls Hoodie",
      "name_parent": "Anime",
      "total": 2667
    },
    {
      "id_sptag": "606716576",
      "name_cl_sptag": "Girls Horns",
      "name_parent": "Anime",
      "total": 2031
    },
    {
      "id_sptag": "-1546073662",
      "name_cl_sptag": "Girls Loli",
      "name_parent": "Anime",
      "total": 2098
    },
    {
      "id_sptag": "-353024394",
      "name_cl_sptag": "Girls Long Hair",
      "name_parent": "Anime",
      "total": 47407
    },
    {
      "id_sptag": "680065126",
      "name_cl_sptag": "Girls Sad",
      "name_parent": "Anime",
      "total": 10506
    },
    {
      "id_sptag": "768898453",
      "name_cl_sptag": "Girls Scarf",
      "name_parent": "Anime",
      "total": 3306
    },
    {
      "id_sptag": "-1230434216",
      "name_cl_sptag": "Girls Smile",
      "name_parent": "Anime",
      "total": 24284
    },
    {
      "id_sptag": "1541647243",
      "name_cl_sptag": "Girls Student",
      "name_parent": "Anime",
      "total": 16308
    },
    {
      "id_sptag": "1078827483",
      "name_cl_sptag": "Girls Tie Bows",
      "name_parent": "Anime",
      "total": 61257
    },
    {
      "id_sptag": "-260062140",
      "name_cl_sptag": "Girls Uniform",
      "name_parent": "Anime",
      "total": 16929
    },
    {
      "id_sptag": "1508952095",
      "name_cl_sptag": "Girls Water Rain",
      "name_parent": "Anime",
      "total": 2954
    },
    {
      "id_sptag": "-2046828957",
      "name_cl_sptag": "Glasses",
      "name_parent": "Anime",
      "total": 150
    },
    {
      "id_sptag": "63311442",
      "name_cl_sptag": "Glove",
      "name_parent": "Anime",
      "total": 164
    },
    {
      "id_sptag": "1257535371",
      "name_cl_sptag": "Hatsune Miku",
      "name_parent": "Anime",
      "total": 884
    },
    {
      "id_sptag": "1367612750",
      "name_cl_sptag": "Headband",
      "name_parent": "Anime",
      "total": 73
    },
    {
      "id_sptag": "959633935",
      "name_cl_sptag": "Joujirou Takajou",
      "name_parent": "Anime",
      "total": 10
    },
    {
      "id_sptag": "2085225201",
      "name_cl_sptag": "Nao Tomori",
      "name_parent": "Anime",
      "total": 56
    },
    {
      "id_sptag": "1677155011",
      "name_cl_sptag": "Petal",
      "name_parent": "Anime",
      "total": 70
    },
    {
      "id_sptag": "-1501705937",
      "name_cl_sptag": "Pigeon",
      "name_parent": "Anime",
      "total": 3
    },
    {
      "id_sptag": "-1216236529",
      "name_cl_sptag": "Sad",
      "name_parent": "Anime",
      "total": 12057
    },
    {
      "id_sptag": "-510858498",
      "name_cl_sptag": "Scarf",
      "name_parent": "Anime",
      "total": 169
    },
    {
      "id_sptag": "29436897",
      "name_cl_sptag": "School Uniform",
      "name_parent": "Anime",
      "total": 467
    },
    {
      "id_sptag": "177416588",
      "name_cl_sptag": "Skirt",
      "name_parent": "Anime",
      "total": 368
    },
    {
      "id_sptag": "1443880616",
      "name_cl_sptag": "Socks",
      "name_parent": "Anime",
      "total": 28
    },
    {
      "id_sptag": "-1331370225",
      "name_cl_sptag": "Sunset",
      "name_parent": "Anime",
      "total": 51
    },
    {
      "id_sptag": "26918368",
      "name_cl_sptag": "Thigh Highs",
      "name_parent": "Anime",
      "total": 211
    },
    {
      "id_sptag": "-1456680780",
      "name_cl_sptag": "Twintails",
      "name_parent": "Anime",
      "total": 386
    },
    {
      "id_sptag": "929761085",
      "name_cl_sptag": "Umbrella",
      "name_parent": "Anime",
      "total": 120
    },
    {
      "id_sptag": "-2114154352",
      "name_cl_sptag": "Water",
      "name_parent": "Anime",
      "total": 98
    },
    {
      "id_sptag": "1596260003",
      "name_cl_sptag": "Yu Otosaka",
      "name_parent": "Anime",
      "total": 16
    },
    {
      "id_sptag": "1136471916",
      "name_cl_sptag": "Yusa Kurobane",
      "name_parent": "Anime",
      "total": 9
    },
    {
      "id_sptag": "-1985234469",
      "name_cl_sptag": "Zero Two Darling in the FranXX",
      "name_parent": "Anime",
      "total": 206
    }
  ]
}